setup.py
algovent_utils/__init__.py
algovent_utils/json_response.py
algovent_utils.egg-info/PKG-INFO
algovent_utils.egg-info/SOURCES.txt
algovent_utils.egg-info/dependency_links.txt
algovent_utils.egg-info/not-zip-safe
algovent_utils.egg-info/requires.txt
algovent_utils.egg-info/top_level.txt