Metadata-Version: 1.0
Name: algovent-utils
Version: 0.12
Summary: utils to support django-algovent framework
Home-page: https://github.com/algovent/algovent_utils
Author: Naveen Bollimpalli
Author-email: naveenbollimpalli@gmail.com
License: MIT
Keywords: rest utilities utils django algovent
Platform: UNKNOWN
